time_tracker/__init__.py
time_tracker/log.py
time_tracker/main.py
time_tracker-0.5.3.dist-info/LICENSE
time_tracker-0.5.3.dist-info/METADATA
time_tracker-0.5.3.dist-info/WHEEL
time_tracker-0.5.3.dist-info/entry_points.txt
time_tracker-0.5.3.dist-info/top_level.txt
time_tracker-0.5.3.dist-info/RECORD
