Metadata-Version: 2.1
Name: time-tracker
Version: 0.5.3
Summary: CLI to track time spent on tasks using pomodoro technique
Requires-Python: >=3.11
License-File: LICENSE
Requires-Dist: mypy >=1.11.2
Requires-Dist: pytest >=8.3.3
Requires-Dist: python-dotenv >=1.0.1
Requires-Dist: rich >=13.9.1
Requires-Dist: ruff >=0.6.8
Requires-Dist: typer >=0.12.5
